[
{
    "model": "cart.orderitem",
    "pk": 21,
    "fields": {
        "created": "2021-04-30T06:34:39.028Z",
        "updated": "2021-04-30T06:34:39.028Z",
        "item": 4,
        "order": 1,
        "quantity": 46
    }
},
{
    "model": "cart.orderitem",
    "pk": 22,
    "fields": {
        "created": "2021-04-30T06:38:10.283Z",
        "updated": "2021-04-30T06:38:10.283Z",
        "item": 3,
        "order": 1,
        "quantity": 65
    }
},
{
    "model": "cart.orderitem",
    "pk": 23,
    "fields": {
        "created": "2021-04-30T06:38:10.283Z",
        "updated": "2021-04-30T07:53:53.641Z",
        "item": 6,
        "order": 1,
        "quantity": 456
    }
},
{
    "model": "cart.orderitem",
    "pk": 24,
    "fields": {
        "created": "2021-04-30T07:54:08.472Z",
        "updated": "2021-04-30T07:54:08.472Z",
        "item": 2,
        "order": 2,
        "quantity": 1
    }
},
{
    "model": "cart.orderitem",
    "pk": 25,
    "fields": {
        "created": "2021-04-30T07:54:32.966Z",
        "updated": "2021-04-30T07:56:19.051Z",
        "item": 3,
        "order": 3,
        "quantity": 1456
    }
},
{
    "model": "cart.orderitem",
    "pk": 26,
    "fields": {
        "created": "2021-04-30T07:54:53.663Z",
        "updated": "2021-04-30T07:54:53.663Z",
        "item": 4,
        "order": 4,
        "quantity": 1
    }
},
{
    "model": "cart.orderitem",
    "pk": 27,
    "fields": {
        "created": "2021-04-30T07:55:14.989Z",
        "updated": "2021-04-30T07:55:14.989Z",
        "item": 2,
        "order": 5,
        "quantity": 1
    }
},
{
    "model": "cart.orderitem",
    "pk": 28,
    "fields": {
        "created": "2021-04-30T07:55:42.376Z",
        "updated": "2021-04-30T07:55:42.376Z",
        "item": 4,
        "order": 5,
        "quantity": 456
    }
},
{
    "model": "cart.orderitem",
    "pk": 29,
    "fields": {
        "created": "2021-04-30T07:55:42.377Z",
        "updated": "2021-04-30T07:55:42.377Z",
        "item": 5,
        "order": 5,
        "quantity": 456
    }
},
{
    "model": "cart.orderitem",
    "pk": 30,
    "fields": {
        "created": "2021-04-30T07:55:42.377Z",
        "updated": "2021-04-30T07:55:42.377Z",
        "item": 6,
        "order": 5,
        "quantity": 5
    }
},
{
    "model": "cart.orderitem",
    "pk": 31,
    "fields": {
        "created": "2021-04-30T07:56:19.054Z",
        "updated": "2021-04-30T07:56:19.054Z",
        "item": 5,
        "order": 3,
        "quantity": 456
    }
},
{
    "model": "cart.orderitem",
    "pk": 32,
    "fields": {
        "created": "2021-04-30T07:56:19.056Z",
        "updated": "2021-04-30T07:56:19.056Z",
        "item": 6,
        "order": 3,
        "quantity": 456
    }
},
{
    "model": "cart.orderitem",
    "pk": 33,
    "fields": {
        "created": "2021-04-30T07:56:41.005Z",
        "updated": "2021-04-30T07:56:41.005Z",
        "item": 5,
        "order": 2,
        "quantity": 465
    }
},
{
    "model": "cart.orderitem",
    "pk": 34,
    "fields": {
        "created": "2021-04-30T07:56:41.006Z",
        "updated": "2021-04-30T07:56:41.006Z",
        "item": 6,
        "order": 2,
        "quantity": 64
    }
},
{
    "model": "cart.orderitem",
    "pk": 35,
    "fields": {
        "created": "2021-04-30T07:56:41.006Z",
        "updated": "2021-04-30T07:56:41.006Z",
        "item": 1,
        "order": 2,
        "quantity": 456
    }
},
{
    "model": "cart.orderitem",
    "pk": 36,
    "fields": {
        "created": "2021-04-30T07:57:01.036Z",
        "updated": "2021-04-30T07:57:01.036Z",
        "item": 6,
        "order": 4,
        "quantity": 65
    }
},
{
    "model": "cart.orderitem",
    "pk": 37,
    "fields": {
        "created": "2021-04-30T07:57:01.036Z",
        "updated": "2021-04-30T07:57:01.036Z",
        "item": 1,
        "order": 4,
        "quantity": 645
    }
}
]
